Metadata-Version: 1.1
Name: simplebloomfilter
Version: 1.0.0
Summary: A simple implementation of Bloom Filter and Scalable Bloom Filter for Python 3.
Home-page: https://github.com/dnanhkhoa/simple-bloom-filter
Author: Khoa Duong
Author-email: dnanhkhoa@live.com
License: MIT
Keywords: bloom-filter scalable-bloom-filter bloomfilter python-3 hashing algorithm data-structure
Platform: UNKNOWN
Classifier: Development Status :: 5 - Production/Stable
Classifier: Intended Audience :: Developers
Classifier: Intended Audience :: Science/Research
Classifier: License :: OSI Approved :: MIT License
Classifier: Programming Language :: Python :: 3
